LICENSE
MANIFEST.in
README.rst
setup.py
django_hallo_markdown.egg-info/PKG-INFO
django_hallo_markdown.egg-info/SOURCES.txt
django_hallo_markdown.egg-info/dependency_links.txt
django_hallo_markdown.egg-info/not-zip-safe
django_hallo_markdown.egg-info/requires.txt
django_hallo_markdown.egg-info/top_level.txt
djhallo/__init__.py
djhallo/models.py
djhallo/widgets.py
djhallo/static/djhallo/djhallo.js
djhallo/static/djhallo/hallo.css
djhallo/static/djhallo/hallo.js
djhallo/static/djhallo/jquery-init.js
djhallo/static/djhallo/showdown.js
djhallo/static/djhallo/to-markdown.js