Metadata-Version: 1.0
Name: django-hallo-markdown
Version: 0.1.1
Summary: Hallo WYSIWYG Markdown widget for Django
Home-page: http://github.com/StefanKjartansson/django-hallo-markdown/
Author: Stefan Kjartansson
Author-email: esteban.supreme@gmail.com
License: UNKNOWN
Platform: UNKNOWN
Classifier: Development Status :: 3 - Alpha
Classifier: Intended Audience :: Developers
Classifier: Environment :: Web Environment
Classifier: Framework :: Django
Classifier: License :: OSI Approved :: MIT License
Classifier: Operating System :: OS Independent
Classifier: Programming Language :: Python
